pretix_fontpackfree/SIL Open Font License.txt
pretix_fontpackfree/Ubuntu Font Licence 1.0.txt
pretix_fontpackfree/__init__.py
pretix_fontpackfree/apps.py
pretix_fontpackfree/signals.py
pretix_fontpackfree/static/pretix_fontpackfree/.gitkeep
pretix_fontpackfree/static/pretix_fontpackfree/DejaVuSans-Bold-webfont.ttf
pretix_fontpackfree/static/pretix_fontpackfree/DejaVuSans-Bold-webfont.woff
pretix_fontpackfree/static/pretix_fontpackfree/DejaVuSans-BoldOblique-webfont.ttf
pretix_fontpackfree/static/pretix_fontpackfree/DejaVuSans-BoldOblique-webfont.woff
pretix_fontpackfree/static/pretix_fontpackfree/DejaVuSans-Oblique-webfont.ttf
pretix_fontpackfree/static/pretix_fontpackfree/DejaVuSans-Oblique-webfont.woff
pretix_fontpackfree/static/pretix_fontpackfree/DejaVuSans-webfont.ttf
pretix_fontpackfree/static/pretix_fontpackfree/DejaVuSans-webfont.woff
pretix_fontpackfree/static/pretix_fontpackfree/DroidSerif-Bold-webfont.ttf
pretix_fontpackfree/static/pretix_fontpackfree/DroidSerif-Bold-webfont.woff
pretix_fontpackfree/static/pretix_fontpackfree/DroidSerif-BoldItalic-webfont.ttf
pretix_fontpackfree/static/pretix_fontpackfree/DroidSerif-BoldItalic-webfont.woff
pretix_fontpackfree/static/pretix_fontpackfree/DroidSerif-Italic-webfont.ttf
pretix_fontpackfree/static/pretix_fontpackfree/DroidSerif-Italic-webfont.woff
pretix_fontpackfree/static/pretix_fontpackfree/DroidSerif-Regular-webfont.ttf
pretix_fontpackfree/static/pretix_fontpackfree/DroidSerif-Regular-webfont.woff
pretix_fontpackfree/static/pretix_fontpackfree/Lato-Bold.ttf
pretix_fontpackfree/static/pretix_fontpackfree/Lato-BoldItalic.ttf
pretix_fontpackfree/static/pretix_fontpackfree/Lato-Italic.ttf
pretix_fontpackfree/static/pretix_fontpackfree/Lato-Regular.ttf
pretix_fontpackfree/static/pretix_fontpackfree/NotoSans-Bold-webfont.ttf
pretix_fontpackfree/static/pretix_fontpackfree/NotoSans-Bold-webfont.woff
pretix_fontpackfree/static/pretix_fontpackfree/NotoSans-Bold-webfont.woff2
pretix_fontpack_free-1.11.0.dist-info/LICENSE
pretix_fontpack_free-1.11.0.dist-info/METADATA
pretix_fontpack_free-1.11.0.dist-info/WHEEL
pretix_fontpack_free-1.11.0.dist-info/entry_points.txt
pretix_fontpack_free-1.11.0.dist-info/top_level.txt
pretix_fontpack_free-1.11.0.dist-info/RECORD
