Metadata-Version: 2.1
Name: pretix-fontpack-free
Version: 1.11.0
Summary: Pack of free fonts for pretix
Author-email: pretix team <support@pretix.eu>
Maintainer-email: pretix team <support@pretix.eu>
License: Copyright 2017 Raphael Michel
Project-URL: homepage, https://github.com/pretix/pretix-fontpack-free
Keywords: pretix
Requires-Python: >=3.9
License-File: LICENSE
